LICENSE
README.md
pyproject.toml
setup.cfg
setup.py
src/inmantals/__init__.py
src/inmantals/jsonrpc.py
src/inmantals/lsp_types.py
src/inmantals/pipeserver.py
src/inmantals/server.py
src/inmantals/tcpserver.py
src/inmantals.egg-info/PKG-INFO
src/inmantals.egg-info/SOURCES.txt
src/inmantals.egg-info/dependency_links.txt
src/inmantals.egg-info/entry_points.txt
src/inmantals.egg-info/requires.txt
src/inmantals.egg-info/top_level.txt
tests/test_smoke.py