Metadata-Version: 2.1
Name: inmantals
Version: 1.6.0
Summary: Inmanta Language Server
Home-page: https://github.com/inmanta/vscode-inmanta
Author: Inmanta
Author-email: code@inmanta.com
License: Apache Software License
Keywords: ide,language-server,vscode,inmanta
Classifier: Development Status :: 5 - Production/Stable
Classifier: Intended Audience :: Developers
Classifier: Intended Audience :: Telecommunications Industry
Classifier: License :: OSI Approved :: Apache Software License
Classifier: Operating System :: OS Independent
Classifier: Topic :: System :: Systems Administration
Classifier: Topic :: Utilities
License-File: LICENSE
Requires-Dist: inmanta-core
Requires-Dist: intervaltree
